sundial/__init__.py
sundial/plotly_theme.py
sundial/sundial.py
sundial_framework-0.2.0.dist-info/WHEEL
sundial_framework-0.2.0.dist-info/METADATA
sundial_framework-0.2.0.dist-info/RECORD
